TlseHypDataSet/__init__.py
TlseHypDataSet/other_data_sets.py
TlseHypDataSet/project_data_set.py
TlseHypDataSet/tlse_hyp_data_set.py
TlseHypDataSet/default_splits/__init__.py
TlseHypDataSet/default_splits/split_1.pkl
TlseHypDataSet/default_splits/split_2.pkl
TlseHypDataSet/default_splits/split_3.pkl
TlseHypDataSet/default_splits/split_4.pkl
TlseHypDataSet/default_splits/split_5.pkl
TlseHypDataSet/default_splits/split_6.pkl
TlseHypDataSet/default_splits/split_7.pkl
TlseHypDataSet/default_splits/split_8.pkl
TlseHypDataSet/dimension_reduction/__init__.py
TlseHypDataSet/dimension_reduction/autoencoders.py
TlseHypDataSet/dimension_reduction/pretrained_params.pt
TlseHypDataSet/ground_truth/__init__.py
TlseHypDataSet/ground_truth/ground_truth.cpg
TlseHypDataSet/ground_truth/ground_truth.dbf
TlseHypDataSet/ground_truth/ground_truth.prj
TlseHypDataSet/ground_truth/ground_truth.shp
TlseHypDataSet/ground_truth/ground_truth.shx
TlseHypDataSet/ground_truth/unlabeled_zones.cpg
TlseHypDataSet/ground_truth/unlabeled_zones.dbf
TlseHypDataSet/ground_truth/unlabeled_zones.prj
TlseHypDataSet/ground_truth/unlabeled_zones.shp
TlseHypDataSet/ground_truth/unlabeled_zones.shx
TlseHypDataSet/metadata/tlse_metadata.txt
TlseHypDataSet/utils/__init__.py
TlseHypDataSet/utils/coreset.py
TlseHypDataSet/utils/dataset.py
TlseHypDataSet/utils/geometry.py
TlseHypDataSet/utils/spectral.py
TlseHypDataSet/utils/spectral_indices.py
TlseHypDataSet/utils/transforms.py
TlseHypDataSet/utils/utils.py
TlseHypDataSet/utils/vis.py
TlseHypDataSet-0.0.6.dist-info/LICENSE.txt
TlseHypDataSet-0.0.6.dist-info/METADATA
TlseHypDataSet-0.0.6.dist-info/WHEEL
TlseHypDataSet-0.0.6.dist-info/top_level.txt
TlseHypDataSet-0.0.6.dist-info/RECORD
