Metadata-Version: 2.1
Name: TlseHypDataSet
Version: 0.0.6
Summary: A Python library to flexibly load the Toulouse Hyperspectral Data Set
Home-page: https://github.com/Romain3Ch216/TlseHypDataSet
Author: Romain Thoreau
Author-email: romain.thoreau@onera.fr
License-File: LICENSE.txt
Requires-Dist: numpy
Requires-Dist: torch
Requires-Dist: rasterio
Requires-Dist: ortools
Requires-Dist: geopandas
Requires-Dist: torchvision
Requires-Dist: matplotlib
Requires-Dist: seaborn
Requires-Dist: h5py
Requires-Dist: scipy
Requires-Dist: scikit-image
